{
	"FechaUTC": "Mar. 11/abr",
	"HoraUTC": "1:25",
	"FechaSemUTC": "Lun. 10/abr",
	"HoraSemUTC": "1:40",
	"semanaUTC": 14,
	"RutinasHorarias": ["ProdsEnRCLV", "LinksEnProd", "MomentoDelAno"],
	"TitulosImgDer": {"10-abr-23": "San José Moscati", "11-abr-23": "San José Moscati", "12-abr-23": "San José Moscati"},
	"FechaHoraUTC": "SI",
	"ImagenDerecha": "SI",
	"HorariosUTC": {"FechaHoraUTC": "00:00", "ImagenDerecha": "06:00"},
	"SemanaUTC": "SI",
	"LinksVencidos": "SI",
	"BorraImagenesSinRegistro": "SI",
	"DiasUTC": {"SemanaUTC": "Sun", "LinksVencidos": "Mon", "BorraImagenesSinRegistro": "Tue"}
}
